base_models/__init__.py
base_models/densenet.py
base_models/mobilenet.py
base_models/resnet.py
base_models/vgg.py
base_models/xception.py
builders/__init__.py
builders/model_builder.py
models/__init__.py
models/bisegnet.py
models/deeplab_v3.py
models/deeplab_v3_plus.py
models/denseaspp.py
models/fcn.py
models/network.py
models/pan.py
models/pspnet.py
models/refinenet.py
models/segnet.py
models/unet.py
utils/__init__.py
utils/data_generator.py
utils/helpers.py
utils/layers.py
utils/learning_rate.py
utils/losses.py
utils/metrics.py
utils/utils.py
semantic_segmentation-0.0.5.dist-info/LICENSE
semantic_segmentation-0.0.5.dist-info/METADATA
semantic_segmentation-0.0.5.dist-info/WHEEL
semantic_segmentation-0.0.5.dist-info/top_level.txt
semantic_segmentation-0.0.5.dist-info/RECORD
