Metadata-Version: 2.1
Name: semantic-segmentation
Version: 0.0.5
Summary: Semantic Segmentation on Tensorflow && Keras
Home-page: https://github.com/luyanger1799/Amazing-Semantic-Segmentation.git
Author: Yang Lu
Author-email: luyanger1799@outlook.com
License: Apache 2,0 License
Platform: all
Requires-Python: >=3.6
